graphene-superstructure/__init__.py
graphene-superstructure/generics.py
graphene-superstructure/generics_utils.py
graphene-superstructure/types.py
graphene-superstructure/utils.py
graphene_framework/__init__.py
graphene_framework/generics.py
graphene_framework/generics_utils.py
graphene_framework/metaclasses.py
graphene_framework/types.py
graphene_framework/utils.py
graphene_superstructure/__init__.py
graphene_superstructure/generics.py
graphene_superstructure/generics_utils.py
graphene_superstructure/types.py
graphene_superstructure/utils.py
graphene_framework-0.0.4.dist-info/LICENSE
graphene_framework-0.0.4.dist-info/METADATA
graphene_framework-0.0.4.dist-info/WHEEL
graphene_framework-0.0.4.dist-info/top_level.txt
graphene_framework-0.0.4.dist-info/RECORD
