Metadata-Version: 2.1
Name: graphene-framework
Version: 0.0.4
Summary: Framework based on graphene
Home-page: https://github.com/Donnyyyyy/graphene-framework
Author: Dmitrii Donetskii
Author-email: donetskiydmitriy@gmail.com
License: UNKNOWN
Platform: UNKNOWN
Classifier: Programming Language :: Python :: 3
Classifier: License :: OSI Approved :: MIT License
Classifier: Operating System :: OS Independent
Requires-Dist: graphene (==2.1.7)
